anyencoder/__init__.py
anyencoder/config.py
anyencoder/encoder.py
anyencoder/label.py
anyencoder/maker.py
anyencoder/reader.py
anyencoder/registry.py
anyencoder/util.py
anyencoder/plugins/__init__.py
anyencoder/plugins/base.py
anyencoder/plugins/bson.py
anyencoder/plugins/bzip2.py
anyencoder/plugins/cloudpickle.py
anyencoder/plugins/dill.py
anyencoder/plugins/gzip.py
anyencoder/plugins/json.py
anyencoder/plugins/msgpack.py
anyencoder/plugins/orjson.py
anyencoder/plugins/pickle.py
anyencoder/plugins/strbyte.py
anyencoder/plugins/ujson.py
anyencoder/plugins/zlib.py
anyencoder-0.0.1.dist-info/LICENSE
anyencoder-0.0.1.dist-info/METADATA
anyencoder-0.0.1.dist-info/WHEEL
anyencoder-0.0.1.dist-info/top_level.txt
anyencoder-0.0.1.dist-info/RECORD
