Metadata-Version: 2.1
Name: anyencoder
Version: 0.0.1
Summary: Dynamic dispatch for object serialization
Home-page: https://www.github.com/andrewschenck/py-anyencoder
Author: Andrew Blair Schenck
Author-email: aschenck@gmail.com
License: UNKNOWN
Platform: UNKNOWN
Classifier: Development Status :: 3 - Alpha
Classifier: Intended Audience :: Developers
Classifier: License :: OSI Approved :: Apache Software License
Classifier: Programming Language :: Python
Classifier: Programming Language :: Python :: 3
Classifier: Programming Language :: Python :: 3.7
Classifier: Programming Language :: Python :: 3.8
Classifier: Topic :: Software Development :: Libraries
Classifier: Topic :: Software Development :: Libraries :: Python Modules
Requires-Python: >=3.7
Requires-Dist: multi-key-dict (>=2.0.3)
